pystorcli/__init__.py
pystorcli/cachevault.py
pystorcli/cmdRunner.py
pystorcli/common.py
pystorcli/errors.py
pystorcli/exc.py
pystorcli/storcli.py
pystorcli/version.py
pystorcli/bin/__init__.py
pystorcli/bin/metrics.py
pystorcli/controller/__init__.py
pystorcli/controller/metrics.py
pystorcli/drive/__init__.py
pystorcli/drive/metrics.py
pystorcli/drive/state.py
pystorcli/enclosure/__init__.py
pystorcli/virtualdrive/__init__.py
pystorcli/virtualdrive/access.py
pystorcli/virtualdrive/metrics.py
pystorcli/virtualdrive/state.py
pystorcli2/.gitignore
pystorcli2/__init__.py
pystorcli2/cachevault.py
pystorcli2/cmdRunner.py
pystorcli2/common.py
pystorcli2/errors.py
pystorcli2/exc.py
pystorcli2/storcli.py
pystorcli2/version.py
pystorcli2/bin/__init__.py
pystorcli2/bin/metrics.py
pystorcli2/controller/__init__.py
pystorcli2/controller/metrics.py
pystorcli2/drive/__init__.py
pystorcli2/drive/metrics.py
pystorcli2/drive/state.py
pystorcli2/enclosure/__init__.py
pystorcli2/virtualdrive/__init__.py
pystorcli2/virtualdrive/access.py
pystorcli2/virtualdrive/metrics.py
pystorcli2/virtualdrive/state.py
pystorcli_mirror/__init__.py
PyStorCLI2-0.6.4.dist-info/LICENSE
PyStorCLI2-0.6.4.dist-info/METADATA
PyStorCLI2-0.6.4.dist-info/WHEEL
PyStorCLI2-0.6.4.dist-info/entry_points.txt
PyStorCLI2-0.6.4.dist-info/top_level.txt
PyStorCLI2-0.6.4.dist-info/RECORD
