Metadata-Version: 2.1
Name: PyStorCLI2
Version: 0.6.4
Summary: StorCLI module wrapper 2
Author-email: Rafael Leira <rafael.leira@naudit.es>, Martin Dojcak <martin.dojcak@lablabs.io>
License: BSD-3-Clause
Project-URL: Homepage, https://github.com/Naudit/pystorcli2
Keywords: storcli,wrapper
Classifier: Programming Language :: Python :: 3
Classifier: Intended Audience :: Developers
Classifier: Intended Audience :: Information Technology
Classifier: Intended Audience :: System Administrators
Classifier: License :: OSI Approved :: BSD License
Classifier: Natural Language :: English
Classifier: Operating System :: POSIX
Classifier: Topic :: System :: Hardware :: Hardware Drivers
Classifier: Topic :: System :: Installation/Setup
Classifier: Topic :: Software Development :: Libraries :: Python Modules
Classifier: Programming Language :: Python
Classifier: Development Status :: 3 - Alpha
Requires-Python: >=3.8
License-File: LICENSE
Provides-Extra: dev
Requires-Dist: pytest ; extra == 'dev'
Requires-Dist: pytest-cov ; extra == 'dev'
Requires-Dist: coveralls ; extra == 'dev'
Requires-Dist: pdoc ; extra == 'dev'
Requires-Dist: mypy ; extra == 'dev'
